black_disable_checker/__main__.py
black_disable_checker-1.1.3.dist-info/LICENSE
black_disable_checker-1.1.3.dist-info/METADATA
black_disable_checker-1.1.3.dist-info/WHEEL
black_disable_checker-1.1.3.dist-info/entry_points.txt
black_disable_checker-1.1.3.dist-info/top_level.txt
black_disable_checker-1.1.3.dist-info/RECORD
