Metadata-Version: 2.1
Name: black-disable-checker
Version: 1.1.3
Summary: That little door knob on your blackened bike shed can also be any color you like; as long as it's black.
Home-page: https://github.com/Pierre-Sassoulas/black-disable-checker/
Author: Pierre Sassoulas
Author-email: pierre.sassoulas@gmail.com
Classifier: Operating System :: OS Independent
Classifier: Intended Audience :: Developers
Classifier: License :: OSI Approved :: MIT License
Classifier: Programming Language :: Python :: 3.7
Classifier: Programming Language :: Python :: 3.8
Classifier: Programming Language :: Python :: 3.9
Classifier: Programming Language :: Python :: 3.10
Classifier: Programming Language :: Python :: 3.11
Classifier: Development Status :: 5 - Production/Stable
License-File: LICENSE
Provides-Extra: test
Requires-Dist: pytest-cov ; extra == 'test'
Requires-Dist: pytest-vcr ; extra == 'test'
Requires-Dist: coverage ; extra == 'test'
Requires-Dist: python-coveralls ; extra == 'test'
Requires-Dist: coveralls ; extra == 'test'
Requires-Dist: pylint (~=2.14.5) ; extra == 'test'
Requires-Dist: pre-commit ; extra == 'test'
Requires-Dist: tbump ; extra == 'test'
